{
  "items": [
    {
      "snippet": {
        "title": "مدير منظمة الصحة العالمية: حان الوقت كي يتعافى العالم، وينبذ \"القومية المضللة\"",
        "thumbnails": {
          "high": {
            "url": "https://i.ytimg.com/vi/YDuVDalFVmw/hqdefault.jpg"
          }
        },
        "resourceId": {
          "videoId": "YDuVDalFVmw"
        }
      }
    },
    {
      "snippet": {
        "title": "دعوة إلى اليمنيين للتكاتف من أجل حل سياسي شامل فيما يحوم شبح المجاعة فوق رؤوس المدنيين",
        "thumbnails": {
          "high": {
            "url": "https://i.ytimg.com/vi/vGt5OBNzlf8/hqdefault.jpg"
          }
        },
        "resourceId": {
          "videoId": "vGt5OBNzlf8"
        }
      }
    },
    {
      "snippet": {
        "title": "رسالة ملهمة لنائبة الأمين العام خلال زيارة نيجيريا",
        "thumbnails": {
          "high": {
            "url": "https://i.ytimg.com/vi/KcivjeuMyrs/hqdefault.jpg"
          }
        },
        "resourceId": {
          "videoId": "KcivjeuMyrs"
        }
      }
    },
    {
      "snippet": {
        "title": "ماذا يتمنى الطفل اللبناني حسين في العام المقبل؟",
        "thumbnails": {
          "high": {
            "url": "https://i.ytimg.com/vi/zq7QRb3jDig/hqdefault.jpg"
          }
        },
        "resourceId": {
          "videoId": "zq7QRb3jDig"
        }
      }
    },
    {
      "snippet": {
        "title": "د. أحمد المنظري يطلع على أوضاع المرضى والعاملين الصحيين في سوريا",
        "thumbnails": {
          "high": {
            "url": "https://i.ytimg.com/vi/8BiIAeqCUZQ/hqdefault.jpg"
          }
        },
        "resourceId": {
          "videoId": "8BiIAeqCUZQ"
        }
      }
    },
    {
      "snippet": {
        "title": "\"عقدة الناجي\" تلاحق المهاجرة الصحفية الفلسطينية السورية بيسان زرزر",
        "thumbnails": {
          "high": {
            "url": "https://i.ytimg.com/vi/F5Q9kFifoU0/hqdefault.jpg"
          }
        },
        "resourceId": {
          "videoId": "F5Q9kFifoU0"
        }
      }
    },
    {
      "snippet": {
        "title": "فاطمة جمعة خميس: مهندسة سودانية تتحدى المألوف وترفض الصور النمطية في مجتمعها",
        "thumbnails": {
          "high": {
            "url": "https://i.ytimg.com/vi/mZsBFoPcpFU/hqdefault.jpg"
          }
        },
        "resourceId": {
          "videoId": "mZsBFoPcpFU"
        }
      }
    },
    {
      "snippet": {
        "title": "منظمة الصحة العالمية تقدم الدعم لمستشفى الحريري في بيروت",
        "thumbnails": {
          "high": {
            "url": "https://i.ytimg.com/vi/5dWovxRCT4w/hqdefault.jpg"
          }
        },
        "resourceId": {
          "videoId": "5dWovxRCT4w"
        }
      }
    },
    {
      "snippet": {
        "title": "مدير عام منظمة الصحة العالمية يخضع للحجر الذاتي.",
        "thumbnails": {
          "high": {
            "url": "https://i.ytimg.com/vi/7tx8Jgh1GWM/hqdefault.jpg"
          }
        },
        "resourceId": {
          "videoId": "7tx8Jgh1GWM"
        }
      }
    },
    {
      "snippet": {
        "title": "بالتعاون مع الأمم المتحدة، المملكة العربية السعودية تتخذ خطوات ملموسة لمكافحة الاتجار بالبشر",
        "thumbnails": {
          "high": {
            "url": "https://i.ytimg.com/vi/jROwp-Zp8rA/hqdefault.jpg"
          }
        },
        "resourceId": {
          "videoId": "jROwp-Zp8rA"
        }
      }
    }
  ]
}
