{
  "items": [
    {
      "snippet": {
        "title": "\"This is a critical moment for the Non-Proliferation Treaty\" - United States on NPT -Media Stakeout",
        "thumbnails": {
          "high": {
            "url": "https://i.ytimg.com/vi/Rf4AL2bqmuk/hqdefault.jpg"
          }
        },
        "resourceId": {
          "videoId": "Rf4AL2bqmuk"
        }
      }
    },
    {
      "snippet": {
        "title": "Black Sea Initiative, Libya & other topics -Daily Press Briefing (1 August 2022)",
        "thumbnails": {
          "high": {
            "url": "https://i.ytimg.com/vi/zNub8Mz_ZKI/hqdefault.jpg"
          }
        },
        "resourceId": {
          "videoId": "zNub8Mz_ZKI"
        }
      }
    },
    {
      "snippet": {
        "title": "'Humanity is one miscalculation away from nuclear annihilation'- UN Chief |Nuclear Non-Proliferation",
        "thumbnails": {
          "high": {
            "url": "https://i.ytimg.com/vi/I0My9xhgxVE/hqdefault.jpg"
          }
        },
        "resourceId": {
          "videoId": "I0My9xhgxVE"
        }
      }
    },
    {
      "snippet": {
        "title": "Ukraine: First commercial ship since February sails from Odesa - UN Chief Press Briefing",
        "thumbnails": {
          "high": {
            "url": "https://i.ytimg.com/vi/cUhbaAqy3ew/hqdefault.jpg"
          }
        },
        "resourceId": {
          "videoId": "cUhbaAqy3ew"
        }
      }
    },
    {
      "snippet": {
        "title": "The situation of Women and Girls in Afghanistan - Press Conference (25 July 2022) | United Nations",
        "thumbnails": {
          "high": {
            "url": "https://i.ytimg.com/vi/PT0-IV_6UDo/hqdefault.jpg"
          }
        },
        "resourceId": {
          "videoId": "PT0-IV_6UDo"
        }
      }
    },
    {
      "snippet": {
        "title": "What are Ocean Buoys and Why are they Extremely Important | United Nations | WMO | Climate Action",
        "thumbnails": {
          "high": {
            "url": "https://i.ytimg.com/vi/OcJ5GdpcosI/hqdefault.jpg"
          }
        },
        "resourceId": {
          "videoId": "OcJ5GdpcosI"
        }
      }
    },
    {
      "snippet": {
        "title": "Ukraine, Afghanistan & other topics - Daily Press Briefing (29 July 2022)",
        "thumbnails": {
          "high": {
            "url": "https://i.ytimg.com/vi/2r7xqlEN_9k/hqdefault.jpg"
          }
        },
        "resourceId": {
          "videoId": "2r7xqlEN_9k"
        }
      }
    },
    {
      "snippet": {
        "title": "Ukraine: Black Sea Grain Initiative  - Press Conference (28 July 2022)",
        "thumbnails": {
          "high": {
            "url": "https://i.ytimg.com/vi/EQkHhJmTxlk/hqdefault.jpg"
          }
        },
        "resourceId": {
          "videoId": "EQkHhJmTxlk"
        }
      }
    },
    {
      "snippet": {
        "title": "Right to a Clean, Healthy & Sustainable Environment & other topics - Daily Briefing (28 July 2022)",
        "thumbnails": {
          "high": {
            "url": "https://i.ytimg.com/vi/oFaYhPkEDrU/hqdefault.jpg"
          }
        },
        "resourceId": {
          "videoId": "oFaYhPkEDrU"
        }
      }
    },
    {
      "snippet": {
        "title": "Democratic Republic of the Congo, Mali & other topics - Daily Briefing (27 July 2022)",
        "thumbnails": {
          "high": {
            "url": "https://i.ytimg.com/vi/LDSGnUEPIYU/hqdefault.jpg"
          }
        },
        "resourceId": {
          "videoId": "LDSGnUEPIYU"
        }
      }
    }
  ]
}
