{
  "items": [
    {
      "snippet": {
        "title": "UN Security Twitter Promo #Shorts",
        "thumbnails": {
          "high": {
            "url": "https://i.ytimg.com/vi/TE-vqte-fq0/hqdefault.jpg"
          }
        },
        "resourceId": {
          "videoId": "TE-vqte-fq0"
        }
      }
    },
    {
      "snippet": {
        "title": "World Humanitarian Day 2022 - UN Chief message",
        "thumbnails": {
          "high": {
            "url": "https://i.ytimg.com/vi/PillH4jjcbQ/hqdefault.jpg"
          }
        },
        "resourceId": {
          "videoId": "PillH4jjcbQ"
        }
      }
    },
    {
      "snippet": {
        "title": "Ukraine, Afghanistan & other topics -  Daily Press Briefing (18 August 2022)",
        "thumbnails": {
          "high": {
            "url": "https://i.ytimg.com/vi/tqE5GRy2D5o/hqdefault.jpg"
          }
        },
        "resourceId": {
          "videoId": "tqE5GRy2D5o"
        }
      }
    },
    {
      "snippet": {
        "title": "UN Special Envoy for Yemen, Hans Grundberg on the extended truce in Yemen #Shorts",
        "thumbnails": {
          "high": {
            "url": "https://i.ytimg.com/vi/UmAyxM6hh44/hqdefault.jpg"
          }
        },
        "resourceId": {
          "videoId": "UmAyxM6hh44"
        }
      }
    },
    {
      "snippet": {
        "title": "Ukraine, Myanmar, Sri Lanka & other topics - Daily Press Briefing (17 August 2022)",
        "thumbnails": {
          "high": {
            "url": "https://i.ytimg.com/vi/EDlp0eNFxE8/hqdefault.jpg"
          }
        },
        "resourceId": {
          "videoId": "EDlp0eNFxE8"
        }
      }
    },
    {
      "snippet": {
        "title": "Ukraine, Black Sea Grain Initiative, Kenya & other topics - Daily Press Briefing (16 August 2022)",
        "thumbnails": {
          "high": {
            "url": "https://i.ytimg.com/vi/srDGqUcP0eM/hqdefault.jpg"
          }
        },
        "resourceId": {
          "videoId": "srDGqUcP0eM"
        }
      }
    },
    {
      "snippet": {
        "title": "Afghanistan: one year since the Taliban takeover  - Press Conference (15 August 2022)",
        "thumbnails": {
          "high": {
            "url": "https://i.ytimg.com/vi/9spDquzJHwA/hqdefault.jpg"
          }
        },
        "resourceId": {
          "videoId": "9spDquzJHwA"
        }
      }
    },
    {
      "snippet": {
        "title": "\"We need to end the conflict, not merely manage it\" - Special Envoy for Yemen | Security Council",
        "thumbnails": {
          "high": {
            "url": "https://i.ytimg.com/vi/gxAUFoY_Qps/hqdefault.jpg"
          }
        },
        "resourceId": {
          "videoId": "gxAUFoY_Qps"
        }
      }
    },
    {
      "snippet": {
        "title": "Ukraine, Mali, Yemen & other topics - Daily Press Briefing (15 August 2022)",
        "thumbnails": {
          "high": {
            "url": "https://i.ytimg.com/vi/VDIH7yY75L8/hqdefault.jpg"
          }
        },
        "resourceId": {
          "videoId": "VDIH7yY75L8"
        }
      }
    },
    {
      "snippet": {
        "title": "Georgia: Joint Security Council Stakeout (15 August 2022) | United Nations",
        "thumbnails": {
          "high": {
            "url": "https://i.ytimg.com/vi/KQtXuo_wcZo/hqdefault.jpg"
          }
        },
        "resourceId": {
          "videoId": "KQtXuo_wcZo"
        }
      }
    }
  ]
}
