{
  "items": [
    {
      "snippet": {
        "title": "Moldova: 'very generous in receiving refugee children' - Director of 'Education Cannot Wait'",
        "thumbnails": {
          "high": {
            "url": "https://i.ytimg.com/vi/EFAgvYo7Uu4/hqdefault.jpg"
          }
        },
        "resourceId": {
          "videoId": "EFAgvYo7Uu4"
        }
      }
    },
    {
      "snippet": {
        "title": "Ukraine, Mali, Central African Republic & other topics - Daily Press briefing (20 April 2022)",
        "thumbnails": {
          "high": {
            "url": "https://i.ytimg.com/vi/7BMVkoh4XiY/hqdefault.jpg"
          }
        },
        "resourceId": {
          "videoId": "7BMVkoh4XiY"
        }
      }
    },
    {
      "snippet": {
        "title": "Ukraine: \"Almost 5 million people have been forced to leave\" – Security Council Briefing (19 April)",
        "thumbnails": {
          "high": {
            "url": "https://i.ytimg.com/vi/-A_NlPvUy5k/hqdefault.jpg"
          }
        },
        "resourceId": {
          "videoId": "-A_NlPvUy5k"
        }
      }
    },
    {
      "snippet": {
        "title": "Ukraine, Afghanistan, Horn of Africa & other topics - Daily Press Briefing (19 April 2022)",
        "thumbnails": {
          "high": {
            "url": "https://i.ytimg.com/vi/Rel9lLKW2mw/hqdefault.jpg"
          }
        },
        "resourceId": {
          "videoId": "Rel9lLKW2mw"
        }
      }
    },
    {
      "snippet": {
        "title": "Ireland on Ukraine - Security Council Media Stakeout (19 April 2022)",
        "thumbnails": {
          "high": {
            "url": "https://i.ytimg.com/vi/XHK7oQF0LK0/hqdefault.jpg"
          }
        },
        "resourceId": {
          "videoId": "XHK7oQF0LK0"
        }
      }
    },
    {
      "snippet": {
        "title": "France and Mexico on Ukraine - Security Council Media Stakeout (19 April 2022)",
        "thumbnails": {
          "high": {
            "url": "https://i.ytimg.com/vi/o1LWNI3Gj_M/hqdefault.jpg"
          }
        },
        "resourceId": {
          "videoId": "o1LWNI3Gj_M"
        }
      }
    },
    {
      "snippet": {
        "title": "Russia on Ukraine - Security Council Media Stakeout (19 April 2022)",
        "thumbnails": {
          "high": {
            "url": "https://i.ytimg.com/vi/M9-bWMNs_Ig/hqdefault.jpg"
          }
        },
        "resourceId": {
          "videoId": "M9-bWMNs_Ig"
        }
      }
    },
    {
      "snippet": {
        "title": "Palestine on Palestine/Israel- Security Council Media Stakeout (19 April 2022)",
        "thumbnails": {
          "high": {
            "url": "https://i.ytimg.com/vi/h8yGRHodnos/hqdefault.jpg"
          }
        },
        "resourceId": {
          "videoId": "h8yGRHodnos"
        }
      }
    },
    {
      "snippet": {
        "title": "Current & former EU members Security Council on Palestine - Joint Security Council Media Stakeout",
        "thumbnails": {
          "high": {
            "url": "https://i.ytimg.com/vi/kZ8zXtPzjdI/hqdefault.jpg"
          }
        },
        "resourceId": {
          "videoId": "kZ8zXtPzjdI"
        }
      }
    },
    {
      "snippet": {
        "title": "Norway on Palestine - Security Council Media Stakeout",
        "thumbnails": {
          "high": {
            "url": "https://i.ytimg.com/vi/LpxSBkM4yrk/hqdefault.jpg"
          }
        },
        "resourceId": {
          "videoId": "LpxSBkM4yrk"
        }
      }
    }
  ]
}
