{
  "items": [
    {
      "snippet": {
        "title": "Russia on Nord Stream Sabotage - Security Council Media Stakeout | United Nations",
        "thumbnails": {
          "high": {
            "url": "https://i.ytimg.com/vi/e0Gx-HCY-I0/hqdefault.jpg"
          }
        },
        "resourceId": {
          "videoId": "e0Gx-HCY-I0"
        }
      }
    },
    {
      "snippet": {
        "title": "United States on Ukraine - Security Council | United Nations",
        "thumbnails": {
          "high": {
            "url": "https://i.ytimg.com/vi/0wWsC8iwupo/hqdefault.jpg"
          }
        },
        "resourceId": {
          "videoId": "0wWsC8iwupo"
        }
      }
    },
    {
      "snippet": {
        "title": "Middle East, Ukraine& other topics - Daily Press Briefing (27 June 2023)",
        "thumbnails": {
          "high": {
            "url": "https://i.ytimg.com/vi/xdEM67hiClw/hqdefault.jpg"
          }
        },
        "resourceId": {
          "videoId": "xdEM67hiClw"
        }
      }
    },
    {
      "snippet": {
        "title": "'Children continued to be disproportionately affected by armed conflict in 2022'- Press Conference",
        "thumbnails": {
          "high": {
            "url": "https://i.ytimg.com/vi/W7NFcTVsQqo/hqdefault.jpg"
          }
        },
        "resourceId": {
          "videoId": "W7NFcTVsQqo"
        }
      }
    },
    {
      "snippet": {
        "title": "Civil Society Townhall with the President of the 77th Session of the UN General Assembly",
        "thumbnails": {
          "high": {
            "url": "https://i.ytimg.com/vi/yV-OrXzQXpg/hqdefault.jpg"
          }
        },
        "resourceId": {
          "videoId": "yV-OrXzQXpg"
        }
      }
    },
    {
      "snippet": {
        "title": "Security Council President on Middle East, West Bank - Security Council | United Nations",
        "thumbnails": {
          "high": {
            "url": "https://i.ytimg.com/vi/jCv7QIKZ0zs/hqdefault.jpg"
          }
        },
        "resourceId": {
          "videoId": "jCv7QIKZ0zs"
        }
      }
    },
    {
      "snippet": {
        "title": "5 Things to Know about United Nations Field Security Coordination",
        "thumbnails": {
          "high": {
            "url": "https://i.ytimg.com/vi/BLDByktItM4/hqdefault.jpg"
          }
        },
        "resourceId": {
          "videoId": "BLDByktItM4"
        }
      }
    },
    {
      "snippet": {
        "title": "Sudan, Syria & other topics - Daily Press Briefing (26 June 2023)",
        "thumbnails": {
          "high": {
            "url": "https://i.ytimg.com/vi/AqQp2w5tEnI/hqdefault.jpg"
          }
        },
        "resourceId": {
          "videoId": "AqQp2w5tEnI"
        }
      }
    },
    {
      "snippet": {
        "title": "Stigma & discrimination of drug users in Afghanistan - UNODC | United Nations | World Drug Report",
        "thumbnails": {
          "high": {
            "url": "https://i.ytimg.com/vi/9iaKcfQcBWg/hqdefault.jpg"
          }
        },
        "resourceId": {
          "videoId": "9iaKcfQcBWg"
        }
      }
    },
    {
      "snippet": {
        "title": "UNDSS Ethiopia’s Collaboration in Action | United Nations",
        "thumbnails": {
          "high": {
            "url": "https://i.ytimg.com/vi/6GhYFVmRxYU/hqdefault.jpg"
          }
        },
        "resourceId": {
          "videoId": "6GhYFVmRxYU"
        }
      }
    }
  ]
}
