{
  "items": [
    {
      "snippet": {
        "title": "🇵🇰 Pakistan - First Right of Reply, UN General Debate, 78th Session | #UNGA",
        "thumbnails": {
          "high": {
            "url": "https://i.ytimg.com/vi/IONapBZPTyw/hqdefault.jpg"
          }
        },
        "resourceId": {
          "videoId": "IONapBZPTyw"
        }
      }
    },
    {
      "snippet": {
        "title": "#UNGA78 General Debate Live (Israel, Pakistan, Iraq, UK, & More) - 22 September 2023",
        "thumbnails": {
          "high": {
            "url": "https://i.ytimg.com/vi/c_khfqBZFXw/hqdefault.jpg"
          }
        },
        "resourceId": {
          "videoId": "c_khfqBZFXw"
        }
      }
    },
    {
      "snippet": {
        "title": "🇮🇷 Iran - First Right of Reply, UN General Debate, 78th Session | #UNGA",
        "thumbnails": {
          "high": {
            "url": "https://i.ytimg.com/vi/dhZKxNmW5IY/hqdefault.jpg"
          }
        },
        "resourceId": {
          "videoId": "dhZKxNmW5IY"
        }
      }
    },
    {
      "snippet": {
        "title": "🇮🇳 India - First Right of Reply, UN General Debate, 78th Session | #UNGA",
        "thumbnails": {
          "high": {
            "url": "https://i.ytimg.com/vi/x5DvSpXLIcE/hqdefault.jpg"
          }
        },
        "resourceId": {
          "videoId": "x5DvSpXLIcE"
        }
      }
    },
    {
      "snippet": {
        "title": "🇨🇷 Costa Rica - Foreign Minister Addresses United Nations General Debate, 78th Session | #UNGA",
        "thumbnails": {
          "high": {
            "url": "https://i.ytimg.com/vi/-oC0FnrIuqI/hqdefault.jpg"
          }
        },
        "resourceId": {
          "videoId": "-oC0FnrIuqI"
        }
      }
    },
    {
      "snippet": {
        "title": "🇧🇸 Bahamas - Foreign Minister Addresses United Nations General Debate, 78th Session | #UNGA",
        "thumbnails": {
          "high": {
            "url": "https://i.ytimg.com/vi/pT8_l0gXBf8/hqdefault.jpg"
          }
        },
        "resourceId": {
          "videoId": "pT8_l0gXBf8"
        }
      }
    },
    {
      "snippet": {
        "title": "🇯🇵 Japan - First Right of Reply, UN General Debate, 78th Session | #UNGA",
        "thumbnails": {
          "high": {
            "url": "https://i.ytimg.com/vi/9HVHcbUKDOo/hqdefault.jpg"
          }
        },
        "resourceId": {
          "videoId": "9HVHcbUKDOo"
        }
      }
    },
    {
      "snippet": {
        "title": "🇸🇪 Sweden - Foreign Minister Addresses United Nations General Debate, 78th Session | #UNGA",
        "thumbnails": {
          "high": {
            "url": "https://i.ytimg.com/vi/q-OVm7WZQoM/hqdefault.jpg"
          }
        },
        "resourceId": {
          "videoId": "q-OVm7WZQoM"
        }
      }
    },
    {
      "snippet": {
        "title": "🇧🇭 Bahrain - Foreign Minister Addresses United Nations General Debate, 78th Session | #UNGA",
        "thumbnails": {
          "high": {
            "url": "https://i.ytimg.com/vi/zNpIoY57Ln8/hqdefault.jpg"
          }
        },
        "resourceId": {
          "videoId": "zNpIoY57Ln8"
        }
      }
    },
    {
      "snippet": {
        "title": "🇦🇺 Australia - Minister for Foreign Affairs Addresses United Nations General Debate, 78th Session",
        "thumbnails": {
          "high": {
            "url": "https://i.ytimg.com/vi/kDP8gF5owjA/hqdefault.jpg"
          }
        },
        "resourceId": {
          "videoId": "kDP8gF5owjA"
        }
      }
    }
  ]
}
