{
  "items": [
    {
      "snippet": {
        "title": "France, Germany and the UK on Iran - Security Council Media Stakeout (30 June 2022)",
        "thumbnails": {
          "high": {
            "url": "https://i.ytimg.com/vi/4CGu8aVuxfM/hqdefault.jpg"
          }
        },
        "resourceId": {
          "videoId": "4CGu8aVuxfM"
        }
      }
    },
    {
      "snippet": {
        "title": "Ireland on the Iran nuclear deal - Security Council Media Stakeout (30 June 2022)",
        "thumbnails": {
          "high": {
            "url": "https://i.ytimg.com/vi/MwESL1iNGLs/hqdefault.jpg"
          }
        },
        "resourceId": {
          "videoId": "MwESL1iNGLs"
        }
      }
    },
    {
      "snippet": {
        "title": "Suriname, Road Safety, Pooled Funds & other topics - Daily Press Briefing (30 June 2022)",
        "thumbnails": {
          "high": {
            "url": "https://i.ytimg.com/vi/uxW2G0EFoE4/hqdefault.jpg"
          }
        },
        "resourceId": {
          "videoId": "uxW2G0EFoE4"
        }
      }
    },
    {
      "snippet": {
        "title": "Climate Action: We wake up fearing that we will be drowned | Small Islands | United Nations",
        "thumbnails": {
          "high": {
            "url": "https://i.ytimg.com/vi/Und2VsqGYcw/hqdefault.jpg"
          }
        },
        "resourceId": {
          "videoId": "Und2VsqGYcw"
        }
      }
    },
    {
      "snippet": {
        "title": "(PREMIERE) Football for the Goals Initiative - Launch | United Nations",
        "thumbnails": {
          "high": {
            "url": "https://i.ytimg.com/vi/aekpx5ZNsHc/hqdefault.jpg"
          }
        },
        "resourceId": {
          "videoId": "aekpx5ZNsHc"
        }
      }
    },
    {
      "snippet": {
        "title": "Poland: Performance & History of Cities - World Urban Forum | Stanisław Hadyna Song & Dance \"Śląsk”",
        "thumbnails": {
          "high": {
            "url": "https://i.ytimg.com/vi/7O3eMncBsso/hqdefault.jpg"
          }
        },
        "resourceId": {
          "videoId": "7O3eMncBsso"
        }
      }
    },
    {
      "snippet": {
        "title": "Bodyboard World Champion: ‘The Ocean is My Best Friend’ | United Nations",
        "thumbnails": {
          "high": {
            "url": "https://i.ytimg.com/vi/jAOlVFR_-qY/hqdefault.jpg"
          }
        },
        "resourceId": {
          "videoId": "jAOlVFR_-qY"
        }
      }
    },
    {
      "snippet": {
        "title": "D.R. Congo Mission Head on the situation in the country - Media Stakeout | United Nations",
        "thumbnails": {
          "high": {
            "url": "https://i.ytimg.com/vi/zkLoV6whh_Y/hqdefault.jpg"
          }
        },
        "resourceId": {
          "videoId": "zkLoV6whh_Y"
        }
      }
    },
    {
      "snippet": {
        "title": "Kenya on the deaths at the Moroccan/Spanish border at Melilla - Security Council | United Nations",
        "thumbnails": {
          "high": {
            "url": "https://i.ytimg.com/vi/3_0Ot3A8lXY/hqdefault.jpg"
          }
        },
        "resourceId": {
          "videoId": "3_0Ot3A8lXY"
        }
      }
    },
    {
      "snippet": {
        "title": "Education Pre-Summit, Central African Republic & other topics - Daily Press Briefing (29 June 2022)",
        "thumbnails": {
          "high": {
            "url": "https://i.ytimg.com/vi/BuJTPHu9G-w/hqdefault.jpg"
          }
        },
        "resourceId": {
          "videoId": "BuJTPHu9G-w"
        }
      }
    }
  ]
}
