{
  "items": [
    {
      "snippet": {
        "title": "West Bank, Türkiye / Syria, Ukraine & other topics - Daily Press Briefing (28 February 2023)",
        "thumbnails": {
          "high": {
            "url": "https://i.ytimg.com/vi/LRehtp66Jrg/hqdefault.jpg"
          }
        },
        "resourceId": {
          "videoId": "LRehtp66Jrg"
        }
      }
    },
    {
      "snippet": {
        "title": "Nigeria: Prevention of Genocide | UN Special Adviser remarks to Nigeria Press Corps | United Nations",
        "thumbnails": {
          "high": {
            "url": "https://i.ytimg.com/vi/fHPk-ZLXFXc/hqdefault.jpg"
          }
        },
        "resourceId": {
          "videoId": "fHPk-ZLXFXc"
        }
      }
    },
    {
      "snippet": {
        "title": "West Bank, Earthquake  & other topics - Daily Press Briefing (27 February 2023)",
        "thumbnails": {
          "high": {
            "url": "https://i.ytimg.com/vi/7vnm_wZsNfY/hqdefault.jpg"
          }
        },
        "resourceId": {
          "videoId": "7vnm_wZsNfY"
        }
      }
    },
    {
      "snippet": {
        "title": "Innovation and technology for gender equality - UN Observance of International Women's Day 2023",
        "thumbnails": {
          "high": {
            "url": "https://i.ytimg.com/vi/c8jP3kEWess/hqdefault_live.jpg"
          }
        },
        "resourceId": {
          "videoId": "c8jP3kEWess"
        }
      }
    },
    {
      "snippet": {
        "title": "Ukraine, Armenia/Azerbaijan, Türkiye / Syria & other topics - Daily Press Briefing (24 Feb 2023)",
        "thumbnails": {
          "high": {
            "url": "https://i.ytimg.com/vi/BGBuNLsk1fE/hqdefault.jpg"
          }
        },
        "resourceId": {
          "videoId": "BGBuNLsk1fE"
        }
      }
    },
    {
      "snippet": {
        "title": "Ukraine - Media Stakeout following Security Council meeting on Ukraine",
        "thumbnails": {
          "high": {
            "url": "https://i.ytimg.com/vi/Mo4HwWSof_I/hqdefault.jpg"
          }
        },
        "resourceId": {
          "videoId": "Mo4HwWSof_I"
        }
      }
    },
    {
      "snippet": {
        "title": "Malta on Ukraine - Security Council Media Stakeout",
        "thumbnails": {
          "high": {
            "url": "https://i.ytimg.com/vi/xGe5LchjmlE/hqdefault.jpg"
          }
        },
        "resourceId": {
          "videoId": "xGe5LchjmlE"
        }
      }
    },
    {
      "snippet": {
        "title": "Ukraine - Security Council meeting (24 February 2023)",
        "thumbnails": {
          "high": {
            "url": "https://i.ytimg.com/vi/sQN6fnGjk10/hqdefault.jpg"
          }
        },
        "resourceId": {
          "videoId": "sQN6fnGjk10"
        }
      }
    },
    {
      "snippet": {
        "title": "EU High Representative on proposed Ukraine Peace Plan - Security Council Media Stakeout",
        "thumbnails": {
          "high": {
            "url": "https://i.ytimg.com/vi/oraC2GUrr6M/hqdefault.jpg"
          }
        },
        "resourceId": {
          "videoId": "oraC2GUrr6M"
        }
      }
    },
    {
      "snippet": {
        "title": "Estonia, Latvia & Lithuania on Ukraine - Security Council Media Stakeout",
        "thumbnails": {
          "high": {
            "url": "https://i.ytimg.com/vi/NrQsCpw_wpE/hqdefault.jpg"
          }
        },
        "resourceId": {
          "videoId": "NrQsCpw_wpE"
        }
      }
    }
  ]
}
