{
  "items": [
    {
      "snippet": {
        "title": "#UNGA78 General Debate Live (USA, Ukraine, Iran, Germany, Japan & More)- 19 September 2023",
        "thumbnails": {
          "high": {
            "url": "https://i.ytimg.com/vi/ZgWMhijIh_k/hqdefault_live.jpg"
          }
        },
        "resourceId": {
          "videoId": "ZgWMhijIh_k"
        }
      }
    },
    {
      "snippet": {
        "title": "🇧🇷 Brazil - President Addresses United Nations General Debate, 78th Session | #UNGA",
        "thumbnails": {
          "high": {
            "url": "https://i.ytimg.com/vi/uQZm_uHRg_k/hqdefault.jpg"
          }
        },
        "resourceId": {
          "videoId": "uQZm_uHRg_k"
        }
      }
    },
    {
      "snippet": {
        "title": "🇺🇳 UN Secretary-General Addresses General Debate, 78th Session | #UNGA",
        "thumbnails": {
          "high": {
            "url": "https://i.ytimg.com/vi/cJ_P43W8Iog/hqdefault.jpg"
          }
        },
        "resourceId": {
          "videoId": "cJ_P43W8Iog"
        }
      }
    },
    {
      "snippet": {
        "title": "🇺🇳 General Assembly President Addresses United Nations General Debate, 78th Session | #UNGA",
        "thumbnails": {
          "high": {
            "url": "https://i.ytimg.com/vi/BJNE8rYlmWo/hqdefault.jpg"
          }
        },
        "resourceId": {
          "videoId": "BJNE8rYlmWo"
        }
      }
    },
    {
      "snippet": {
        "title": "Natalie Portman on Empowering Women & Girls Everywhere | SDG Media Zone | United Nations",
        "thumbnails": {
          "high": {
            "url": "https://i.ytimg.com/vi/7ZPDXNrtNsM/hqdefault.jpg"
          }
        },
        "resourceId": {
          "videoId": "7ZPDXNrtNsM"
        }
      }
    },
    {
      "snippet": {
        "title": "Nyle Di Marco- Disabilities & Human Rights | Sustainable Development Goals | United Nations",
        "thumbnails": {
          "high": {
            "url": "https://i.ytimg.com/vi/8bbG1KdSJ4o/hqdefault.jpg"
          }
        },
        "resourceId": {
          "videoId": "8bbG1KdSJ4o"
        }
      }
    },
    {
      "snippet": {
        "title": "#UNGA78 Halftime Show: Inspiring Action | United Nations",
        "thumbnails": {
          "high": {
            "url": "https://i.ytimg.com/vi/Y0Eoz2hqTos/hqdefault.jpg"
          }
        },
        "resourceId": {
          "videoId": "Y0Eoz2hqTos"
        }
      }
    },
    {
      "snippet": {
        "title": "Ecuadorian Amazon Defender of Biodiversity Protection - Helena Gualinga | SDG Halftime Show | UN",
        "thumbnails": {
          "high": {
            "url": "https://i.ytimg.com/vi/3ej7mCpUEZ8/hqdefault.jpg"
          }
        },
        "resourceId": {
          "videoId": "3ej7mCpUEZ8"
        }
      }
    },
    {
      "snippet": {
        "title": "Orlando Bloom: Importance of Education For Children | #UNGA78 Halftime Show | United Nations",
        "thumbnails": {
          "high": {
            "url": "https://i.ytimg.com/vi/N9AkfNMLeVA/hqdefault.jpg"
          }
        },
        "resourceId": {
          "videoId": "N9AkfNMLeVA"
        }
      }
    },
    {
      "snippet": {
        "title": "ICJ: Ukraine v. Russian Federation: Allegations of Genocide | 1st Round of Oral Arguments by Russia",
        "thumbnails": {
          "high": {
            "url": "https://i.ytimg.com/vi/VTjit5jmTYU/hqdefault.jpg"
          }
        },
        "resourceId": {
          "videoId": "VTjit5jmTYU"
        }
      }
    }
  ]
}
