{
  "items": [
    {
      "snippet": {
        "title": "European Union on the General Assembly vote to suspend Russia from the Human Rights Council",
        "thumbnails": {
          "high": {
            "url": "https://i.ytimg.com/vi/w3NW_7FcmmQ/hqdefault.jpg"
          }
        },
        "resourceId": {
          "videoId": "w3NW_7FcmmQ"
        }
      }
    },
    {
      "snippet": {
        "title": "Mexico on the General Assembly vote to suspend Russia from the Human Rights Council",
        "thumbnails": {
          "high": {
            "url": "https://i.ytimg.com/vi/7DqthMaoZ9Y/hqdefault.jpg"
          }
        },
        "resourceId": {
          "videoId": "7DqthMaoZ9Y"
        }
      }
    },
    {
      "snippet": {
        "title": "Ukraine on the General Assembly vote to suspend Russia from the Human Rights Council",
        "thumbnails": {
          "high": {
            "url": "https://i.ytimg.com/vi/8Ugx1hClQdU/hqdefault.jpg"
          }
        },
        "resourceId": {
          "videoId": "8Ugx1hClQdU"
        }
      }
    },
    {
      "snippet": {
        "title": "Ukraine, Yemen, Security Council & other topics - Daily Briefing (7 April 2022)",
        "thumbnails": {
          "high": {
            "url": "https://i.ytimg.com/vi/2WE5qcB_3Mk/hqdefault.jpg"
          }
        },
        "resourceId": {
          "videoId": "2WE5qcB_3Mk"
        }
      }
    },
    {
      "snippet": {
        "title": "Ukraine: UN General Assembly, Eleventh Emergency Special Session resumed (7 April 2022)",
        "thumbnails": {
          "high": {
            "url": "https://i.ytimg.com/vi/9FGQiXVy-rE/hqdefault.jpg"
          }
        },
        "resourceId": {
          "videoId": "9FGQiXVy-rE"
        }
      }
    },
    {
      "snippet": {
        "title": "Voices of Change Ashley Lashley: The health of our people and our environment are all interconnected",
        "thumbnails": {
          "high": {
            "url": "https://i.ytimg.com/vi/w5js4rdaST8/hqdefault.jpg"
          }
        },
        "resourceId": {
          "videoId": "w5js4rdaST8"
        }
      }
    },
    {
      "snippet": {
        "title": "Commemoration of the International Day of Reflection on 1994 Genocide Against the Tutsi in Rwanda",
        "thumbnails": {
          "high": {
            "url": "https://i.ytimg.com/vi/v-coSJMJaS0/hqdefault.jpg"
          }
        },
        "resourceId": {
          "videoId": "v-coSJMJaS0"
        }
      }
    },
    {
      "snippet": {
        "title": "A journey into UN Peacekeeping’s Protection of Civilians work in Mali",
        "thumbnails": {
          "high": {
            "url": "https://i.ytimg.com/vi/OEU_MdMrBy4/hqdefault.jpg"
          }
        },
        "resourceId": {
          "videoId": "OEU_MdMrBy4"
        }
      }
    },
    {
      "snippet": {
        "title": "Ethiopia, Somalia, Ukraine & other topics - Daily Press Briefing (6 April 2022)",
        "thumbnails": {
          "high": {
            "url": "https://i.ytimg.com/vi/gCnDPUZA0BM/hqdefault.jpg"
          }
        },
        "resourceId": {
          "videoId": "gCnDPUZA0BM"
        }
      }
    },
    {
      "snippet": {
        "title": "Romania: Pushing back at anti-Roma hate speech | Say #NoToHate | United Nations",
        "thumbnails": {
          "high": {
            "url": "https://i.ytimg.com/vi/ajgdhtrmbiU/hqdefault.jpg"
          }
        },
        "resourceId": {
          "videoId": "ajgdhtrmbiU"
        }
      }
    }
  ]
}
