{
  "items": [
    {
      "snippet": {
        "title": "\"Nearly half of children in Ukraine may be at risk of not having enough food\"-UNICEF |United Nations",
        "thumbnails": {
          "high": {
            "url": "https://i.ytimg.com/vi/D5qYwgv48XM/hqdefault.jpg"
          }
        },
        "resourceId": {
          "videoId": "D5qYwgv48XM"
        }
      }
    },
    {
      "snippet": {
        "title": "\"Brutality against Ukrainian civilians has raised all red flags\" - UN Women Chief | United Nations",
        "thumbnails": {
          "high": {
            "url": "https://i.ytimg.com/vi/YurnAeK76u8/hqdefault.jpg"
          }
        },
        "resourceId": {
          "videoId": "YurnAeK76u8"
        }
      }
    },
    {
      "snippet": {
        "title": "Norway on Ukraine's Women and Children - Security Council Media Stakeout (11 April 2022)",
        "thumbnails": {
          "high": {
            "url": "https://i.ytimg.com/vi/vjoqlc-TI9g/hqdefault.jpg"
          }
        },
        "resourceId": {
          "videoId": "vjoqlc-TI9g"
        }
      }
    },
    {
      "snippet": {
        "title": "Yemen: 'optimism in operation to salvage the Safer tanker' - Press Conference | United Nations",
        "thumbnails": {
          "high": {
            "url": "https://i.ytimg.com/vi/b1KnCiVGSkc/hqdefault.jpg"
          }
        },
        "resourceId": {
          "videoId": "b1KnCiVGSkc"
        }
      }
    },
    {
      "snippet": {
        "title": "World food commodity prices highest levels ever - Food Price Index Press Conference (8 April 2022)",
        "thumbnails": {
          "high": {
            "url": "https://i.ytimg.com/vi/NqCObPg6gbk/hqdefault.jpg"
          }
        },
        "resourceId": {
          "videoId": "NqCObPg6gbk"
        }
      }
    },
    {
      "snippet": {
        "title": "Ukraine: UN Humanitarian Chief Decries 'Crime Scene,' Urges Ceasefire",
        "thumbnails": {
          "high": {
            "url": "https://i.ytimg.com/vi/Y454xC8rtu0/hqdefault.jpg"
          }
        },
        "resourceId": {
          "videoId": "Y454xC8rtu0"
        }
      }
    },
    {
      "snippet": {
        "title": "Ukraine, Somalia, Israel & other topics - Daily Briefing (8 April 2022)",
        "thumbnails": {
          "high": {
            "url": "https://i.ytimg.com/vi/619muUQW29Y/hqdefault.jpg"
          }
        },
        "resourceId": {
          "videoId": "619muUQW29Y"
        }
      }
    },
    {
      "snippet": {
        "title": "How the UN helps people around the world | United Nations |#Shorts",
        "thumbnails": {
          "high": {
            "url": "https://i.ytimg.com/vi/RfxIh6O3374/hqdefault.jpg"
          }
        },
        "resourceId": {
          "videoId": "RfxIh6O3374"
        }
      }
    },
    {
      "snippet": {
        "title": "Syria: 'fate of tens of thousands of Syrians remains unknown' -UN High Commissioner for Human Rights",
        "thumbnails": {
          "high": {
            "url": "https://i.ytimg.com/vi/Qv7SLNSwp4o/hqdefault.jpg"
          }
        },
        "resourceId": {
          "videoId": "Qv7SLNSwp4o"
        }
      }
    },
    {
      "snippet": {
        "title": "International Romani Union 2022 - UN Chief Message | United Nations",
        "thumbnails": {
          "high": {
            "url": "https://i.ytimg.com/vi/WH_1WMn1E7c/hqdefault.jpg"
          }
        },
        "resourceId": {
          "videoId": "WH_1WMn1E7c"
        }
      }
    }
  ]
}
