{
  "items": [
    {
      "snippet": {
        "title": "L'importance du rôle des femmes dans la construction et le maintien de la paix",
        "thumbnails": {
          "high": {
            "url": "https://i.ytimg.com/vi/gaCLuiT3W7g/hqdefault.jpg"
          }
        },
        "resourceId": {
          "videoId": "gaCLuiT3W7g"
        }
      }
    },
    {
      "snippet": {
        "title": "24 Octobre - Journée des Nations Unies",
        "thumbnails": {
          "high": {
            "url": "https://i.ytimg.com/vi/jpL8TuS34HY/hqdefault.jpg"
          }
        },
        "resourceId": {
          "videoId": "jpL8TuS34HY"
        }
      }
    },
    {
      "snippet": {
        "title": "Journée mondiale de l'alimentation",
        "thumbnails": {
          "high": {
            "url": "https://i.ytimg.com/vi/__Sow3bemj4/hqdefault.jpg"
          }
        },
        "resourceId": {
          "videoId": "__Sow3bemj4"
        }
      }
    },
    {
      "snippet": {
        "title": "Débat sur la consolidation de la paix et la paix durable",
        "thumbnails": {
          "high": {
            "url": "https://i.ytimg.com/vi/90Cj2kFuviY/hqdefault.jpg"
          }
        },
        "resourceId": {
          "videoId": "90Cj2kFuviY"
        }
      }
    },
    {
      "snippet": {
        "title": "Assurer des soins de santé mentale de qualité pour tous, partout",
        "thumbnails": {
          "high": {
            "url": "https://i.ytimg.com/vi/yM0b_CyfNdk/hqdefault.jpg"
          }
        },
        "resourceId": {
          "videoId": "yM0b_CyfNdk"
        }
      }
    },
    {
      "snippet": {
        "title": "Les Nations Unies lancent une stratégie pour atteindre l'équité vaccinale au niveau mondial",
        "thumbnails": {
          "high": {
            "url": "https://i.ytimg.com/vi/yfKHWLlYo7A/hqdefault.jpg"
          }
        },
        "resourceId": {
          "videoId": "yfKHWLlYo7A"
        }
      }
    },
    {
      "snippet": {
        "title": "Soutenir l'avenir de l'éducation des filles en Afghanistan",
        "thumbnails": {
          "high": {
            "url": "https://i.ytimg.com/vi/fdOiQ3bw4V0/hqdefault.jpg"
          }
        },
        "resourceId": {
          "videoId": "fdOiQ3bw4V0"
        }
      }
    },
    {
      "snippet": {
        "title": "« Les enseignants au cœur de la relance de l’éducation »",
        "thumbnails": {
          "high": {
            "url": "https://i.ytimg.com/vi/n4JBn4h5OW8/hqdefault.jpg"
          }
        },
        "resourceId": {
          "videoId": "n4JBn4h5OW8"
        }
      }
    },
    {
      "snippet": {
        "title": "Le Chef de l'ONU visite des sites touchés par le climat à la Barbade",
        "thumbnails": {
          "high": {
            "url": "https://i.ytimg.com/vi/VQ5E44etHWY/hqdefault.jpg"
          }
        },
        "resourceId": {
          "videoId": "VQ5E44etHWY"
        }
      }
    },
    {
      "snippet": {
        "title": "AG76: 191 dirigeants à l'Assemblée générale de l'ONU",
        "thumbnails": {
          "high": {
            "url": "https://i.ytimg.com/vi/gw87XnPFuFU/hqdefault.jpg"
          }
        },
        "resourceId": {
          "videoId": "gw87XnPFuFU"
        }
      }
    }
  ]
}
