{
  "items": [
    {
      "snippet": {
        "title": "Les femmes dans la diplomatie : une force pour la paix",
        "thumbnails": {
          "high": {
            "url": "https://i.ytimg.com/vi/nDvZcr7nzHA/hqdefault.jpg"
          }
        },
        "resourceId": {
          "videoId": "nDvZcr7nzHA"
        }
      }
    },
    {
      "snippet": {
        "title": "DISCOURS DE HAINE : QUAND LES MOTS TUENT",
        "thumbnails": {
          "high": {
            "url": "https://i.ytimg.com/vi/Wveo6MyYMUg/hqdefault.jpg"
          }
        },
        "resourceId": {
          "videoId": "Wveo6MyYMUg"
        }
      }
    },
    {
      "snippet": {
        "title": "Journée internationale du yoga : le yoga est pour tout le monde",
        "thumbnails": {
          "high": {
            "url": "https://i.ytimg.com/vi/n7q9-qccmTI/hqdefault.jpg"
          }
        },
        "resourceId": {
          "videoId": "n7q9-qccmTI"
        }
      }
    },
    {
      "snippet": {
        "title": "RDC : le HCR échange avec des déplacés au Nord-Kivu",
        "thumbnails": {
          "high": {
            "url": "https://i.ytimg.com/vi/UTTAaLNDhUk/hqdefault.jpg"
          }
        },
        "resourceId": {
          "videoId": "UTTAaLNDhUk"
        }
      }
    },
    {
      "snippet": {
        "title": "Promouvoir l'égalité : Prix du Défenseur militaire de l'égalité des sexes de l’ONU pour 2022",
        "thumbnails": {
          "high": {
            "url": "https://i.ytimg.com/vi/6Rbgjm_JCHg/hqdefault.jpg"
          }
        },
        "resourceId": {
          "videoId": "6Rbgjm_JCHg"
        }
      }
    },
    {
      "snippet": {
        "title": "Que se passe-t-il au Soudan  ? 5 faits",
        "thumbnails": {
          "high": {
            "url": "https://i.ytimg.com/vi/WBvz7i6XeYg/hqdefault.jpg"
          }
        },
        "resourceId": {
          "videoId": "WBvz7i6XeYg"
        }
      }
    },
    {
      "snippet": {
        "title": "Rapport des Nations Unies sur la Population : 5 faits",
        "thumbnails": {
          "high": {
            "url": "https://i.ytimg.com/vi/TMjxUzOGSNk/hqdefault.jpg"
          }
        },
        "resourceId": {
          "videoId": "TMjxUzOGSNk"
        }
      }
    },
    {
      "snippet": {
        "title": "Immaculée Songa :  survivante du génocide de 1994 contre les Tutsis au Rwanda",
        "thumbnails": {
          "high": {
            "url": "https://i.ytimg.com/vi/gf2nPRfMGRI/hqdefault.jpg"
          }
        },
        "resourceId": {
          "videoId": "gf2nPRfMGRI"
        }
      }
    },
    {
      "snippet": {
        "title": "Visite de solidarité pour le ramadan : le chef de l'ONU appelle à l'aide à la Somalie",
        "thumbnails": {
          "high": {
            "url": "https://i.ytimg.com/vi/f2M5rCx04AU/hqdefault.jpg"
          }
        },
        "resourceId": {
          "videoId": "f2M5rCx04AU"
        }
      }
    },
    {
      "snippet": {
        "title": "La mission en RDC (MONUSCO) se renforce face à la désinformation",
        "thumbnails": {
          "high": {
            "url": "https://i.ytimg.com/vi/hpvITKtSxX4/hqdefault.jpg"
          }
        },
        "resourceId": {
          "videoId": "hpvITKtSxX4"
        }
      }
    }
  ]
}
