{
  "items": [
    {
      "snippet": {
        "title": "COP26: « le changement climatique, ça nous concerne tous  »",
        "thumbnails": {
          "high": {
            "url": "https://i.ytimg.com/vi/n2m24lSnhLg/hqdefault.jpg"
          }
        },
        "resourceId": {
          "videoId": "n2m24lSnhLg"
        }
      }
    },
    {
      "snippet": {
        "title": "COP26 : 500 actions prévues dans le plan climat de la ville de Paris",
        "thumbnails": {
          "high": {
            "url": "https://i.ytimg.com/vi/M0zPLxmHApg/hqdefault.jpg"
          }
        },
        "resourceId": {
          "videoId": "M0zPLxmHApg"
        }
      }
    },
    {
      "snippet": {
        "title": "SURINTENDANTE SANGYA MALLA, FEMME POLICIÈRE DE l'ONU DE 2021",
        "thumbnails": {
          "high": {
            "url": "https://i.ytimg.com/vi/O57JxxqKepg/hqdefault.jpg"
          }
        },
        "resourceId": {
          "videoId": "O57JxxqKepg"
        }
      }
    },
    {
      "snippet": {
        "title": "COP26 : Petites îles, grand impact sur l'action climatique",
        "thumbnails": {
          "high": {
            "url": "https://i.ytimg.com/vi/mfLRRD4OWIA/hqdefault.jpg"
          }
        },
        "resourceId": {
          "videoId": "mfLRRD4OWIA"
        }
      }
    },
    {
      "snippet": {
        "title": "Régler un différend devant la CIJ, c'est mieux qu'un conflit armé",
        "thumbnails": {
          "high": {
            "url": "https://i.ytimg.com/vi/JWat83c_vWc/hqdefault.jpg"
          }
        },
        "resourceId": {
          "videoId": "JWat83c_vWc"
        }
      }
    },
    {
      "snippet": {
        "title": "COP26 :  Prendre les plus grandes décisions sur la crise climatique",
        "thumbnails": {
          "high": {
            "url": "https://i.ytimg.com/vi/dYEiu0skYO0/hqdefault.jpg"
          }
        },
        "resourceId": {
          "videoId": "dYEiu0skYO0"
        }
      }
    },
    {
      "snippet": {
        "title": "Forêts, alimentation et agriculture : comment vaincre la crise climatique ?",
        "thumbnails": {
          "high": {
            "url": "https://i.ytimg.com/vi/OU_kbTYMPxw/hqdefault.jpg"
          }
        },
        "resourceId": {
          "videoId": "OU_kbTYMPxw"
        }
      }
    },
    {
      "snippet": {
        "title": "Agir pour le climat - pour les personnes, la planète et la prospérité",
        "thumbnails": {
          "high": {
            "url": "https://i.ytimg.com/vi/xfFh1-Y2nCo/hqdefault.jpg"
          }
        },
        "resourceId": {
          "videoId": "xfFh1-Y2nCo"
        }
      }
    },
    {
      "snippet": {
        "title": "L'importance du rôle des femmes dans la construction et le maintien de la paix",
        "thumbnails": {
          "high": {
            "url": "https://i.ytimg.com/vi/gaCLuiT3W7g/hqdefault.jpg"
          }
        },
        "resourceId": {
          "videoId": "gaCLuiT3W7g"
        }
      }
    },
    {
      "snippet": {
        "title": "24 Octobre - Journée des Nations Unies",
        "thumbnails": {
          "high": {
            "url": "https://i.ytimg.com/vi/jpL8TuS34HY/hqdefault.jpg"
          }
        },
        "resourceId": {
          "videoId": "jpL8TuS34HY"
        }
      }
    }
  ]
}
