{
  "items": [
    {
      "snippet": {
        "title": "Relatório de População da ONU: 5 fatos importantes",
        "thumbnails": {
          "high": {
            "url": "https://i.ytimg.com/vi/SPHJ-zkpQIE/hqdefault.jpg"
          }
        },
        "resourceId": {
          "videoId": "SPHJ-zkpQIE"
        }
      }
    },
    {
      "snippet": {
        "title": "Diretora do Unfpa em Genebra fala à ONU News sobre novas dinâmicas populacionais",
        "thumbnails": {
          "high": {
            "url": "https://i.ytimg.com/vi/DDcYlkAMFzE/hqdefault.jpg"
          }
        },
        "resourceId": {
          "videoId": "DDcYlkAMFzE"
        }
      }
    },
    {
      "snippet": {
        "title": "Relatório Estado da População Mundial 2023",
        "thumbnails": {
          "high": {
            "url": "https://i.ytimg.com/vi/o5UmIM-TjDg/hqdefault.jpg"
          }
        },
        "resourceId": {
          "videoId": "o5UmIM-TjDg"
        }
      }
    },
    {
      "snippet": {
        "title": "Portugal no Fórum sobre Financiamento para o Desenvolvimento",
        "thumbnails": {
          "high": {
            "url": "https://i.ytimg.com/vi/mznZ4erAR3o/hqdefault.jpg"
          }
        },
        "resourceId": {
          "videoId": "mznZ4erAR3o"
        }
      }
    },
    {
      "snippet": {
        "title": "Brasil participa de Fórum Permanente sobre Questões Indígenas",
        "thumbnails": {
          "high": {
            "url": "https://i.ytimg.com/vi/yGSsjzJ3zoE/hqdefault.jpg"
          }
        },
        "resourceId": {
          "videoId": "yGSsjzJ3zoE"
        }
      }
    },
    {
      "snippet": {
        "title": "Os povos indígenas são os maiores guardiões do planeta e da floresta, diz ministra Sonia Guajajara",
        "thumbnails": {
          "high": {
            "url": "https://i.ytimg.com/vi/8BIjubtSO_g/hqdefault.jpg"
          }
        },
        "resourceId": {
          "videoId": "8BIjubtSO_g"
        }
      }
    },
    {
      "snippet": {
        "title": "Assista à íntegra da entrevista exclusiva do general da Monusco",
        "thumbnails": {
          "high": {
            "url": "https://i.ytimg.com/vi/n3IG4ox80v4/hqdefault.jpg"
          }
        },
        "resourceId": {
          "videoId": "n3IG4ox80v4"
        }
      }
    },
    {
      "snippet": {
        "title": "Destaque ONU News: Dia Mundial da Doença de Chagas, OIT no Brasil e aquecimento global",
        "thumbnails": {
          "high": {
            "url": "https://i.ytimg.com/vi/iA-1G2nZhjo/hqdefault.jpg"
          }
        },
        "resourceId": {
          "videoId": "iA-1G2nZhjo"
        }
      }
    },
    {
      "snippet": {
        "title": "Em viagem pela Somália, Guterres reforça apoio da ONU ao país",
        "thumbnails": {
          "high": {
            "url": "https://i.ytimg.com/vi/Y0FAHwFMFdA/hqdefault.jpg"
          }
        },
        "resourceId": {
          "videoId": "Y0FAHwFMFdA"
        }
      }
    },
    {
      "snippet": {
        "title": "Destaque ONU News: secretário-geral na Somália, tráfico de drogas na África e turbulência financeira",
        "thumbnails": {
          "high": {
            "url": "https://i.ytimg.com/vi/yvrHgULZ8JY/hqdefault.jpg"
          }
        },
        "resourceId": {
          "videoId": "yvrHgULZ8JY"
        }
      }
    }
  ]
}
