{
 "items": [
  {
   "snippet": {
    "title": "Primeiro-ministro de Cabo Verde diz à ONU News que Cplp desperta mais e mais interesse",
    "thumbnails": {
     "high": {
      "url": "https://i.ytimg.com/vi/-qcR5-F1_zM/hqdefault.jpg"
     }
    },
    "resourceId": {
     "videoId": "-qcR5-F1_zM"
    }
   }
  },
  {
   "snippet": {
    "title": "Dia 5 - 74ª sessão da Assembleia Geral da ONU",
    "thumbnails": {
     "high": {
      "url": "https://i.ytimg.com/vi/tWXoNX0W7HY/hqdefault.jpg"
     }
    },
    "resourceId": {
     "videoId": "tWXoNX0W7HY"
    }
   }
  },
  {
   "snippet": {
    "title": "Íntegra do discurso de  Cabo Verde nas Nações Unidas",
    "thumbnails": {
     "high": {
      "url": "https://i.ytimg.com/vi/WW94iFW9BzA/hqdefault.jpg"
     }
    },
    "resourceId": {
     "videoId": "WW94iFW9BzA"
    }
   }
  },
  {
   "snippet": {
    "title": "Ministro de Portugal otimista com o crescimento da língua portuguesa nas próximas décadas",
    "thumbnails": {
     "high": {
      "url": "https://i.ytimg.com/vi/JZJYDi8rY98/hqdefault.jpg"
     }
    },
    "resourceId": {
     "videoId": "JZJYDi8rY98"
    }
   }
  },
  {
   "snippet": {
    "title": "Ministro português comenta missões de paz, estratégia de ação climática, migração e Venezuela",
    "thumbnails": {
     "high": {
      "url": "https://i.ytimg.com/vi/MuAMAMptmrQ/hqdefault.jpg"
     }
    },
    "resourceId": {
     "videoId": "MuAMAMptmrQ"
    }
   }
  },
  {
   "snippet": {
    "title": "Dia 4 - 74ª sessão da Assembleia Geral da ONU",
    "thumbnails": {
     "high": {
      "url": "https://i.ytimg.com/vi/XZYXahfa1So/hqdefault.jpg"
     }
    },
    "resourceId": {
     "videoId": "XZYXahfa1So"
    }
   }
  },
  {
   "snippet": {
    "title": "Lugar de mulher é na política, diz ministra de São Tomé e Príncipe",
    "thumbnails": {
     "high": {
      "url": "https://i.ytimg.com/vi/LMoupIjk8GA/hqdefault.jpg"
     }
    },
    "resourceId": {
     "videoId": "LMoupIjk8GA"
    }
   }
  },
  {
   "snippet": {
    "title": "Íntegra do discurso de São Tomé e Príncipe nas Nações Unidas",
    "thumbnails": {
     "high": {
      "url": "https://i.ytimg.com/vi/PHCUqoQDLPo/hqdefault.jpg"
     }
    },
    "resourceId": {
     "videoId": "PHCUqoQDLPo"
    }
   }
  },
  {
   "snippet": {
    "title": "Ministra de São Tomé e Príncipe fala à ONU News sobre discurso do país na Assembleia Geral",
    "thumbnails": {
     "high": {
      "url": "https://i.ytimg.com/vi/tGSvZNMAl1M/hqdefault.jpg"
     }
    },
    "resourceId": {
     "videoId": "tGSvZNMAl1M"
    }
   }
  },
  {
   "snippet": {
    "title": "Dia 3 - 74ª sessão da Assembleia Geral da ONU",
    "thumbnails": {
     "high": {
      "url": "https://i.ytimg.com/vi/aDITtFJTmm0/hqdefault.jpg"
     }
    },
    "resourceId": {
     "videoId": "aDITtFJTmm0"
    }
   }
  }
 ]
}
