{
 "items": [
  {
   "snippet": {
    "title": "Desigualdade atinge mais de 70% da população global",
    "thumbnails": {
     "high": {
      "url": "https://i.ytimg.com/vi/Li-SES39Z6E/hqdefault.jpg"
     }
    },
    "resourceId": {
     "videoId": "Li-SES39Z6E"
    }
   }
  },
  {
   "snippet": {
    "title": "OMS faz reunião de emergência sobre coronavírus",
    "thumbnails": {
     "high": {
      "url": "https://i.ytimg.com/vi/g9MJGUELqVM/hqdefault.jpg"
     }
    },
    "resourceId": {
     "videoId": "g9MJGUELqVM"
    }
   }
  },
  {
   "snippet": {
    "title": "Guterres pede aos Estados-membros que ouçam as pessoas",
    "thumbnails": {
     "high": {
      "url": "https://i.ytimg.com/vi/3mD5UK98Ebs/hqdefault.jpg"
     }
    },
    "resourceId": {
     "videoId": "3mD5UK98Ebs"
    }
   }
  },
  {
   "snippet": {
    "title": "Reunião de emergência sobre coronavírus, aumenta a desigualdade no mundo e Guterres fala sobre Líbia",
    "thumbnails": {
     "high": {
      "url": "https://i.ytimg.com/vi/xRA2M0hcpxY/hqdefault.jpg"
     }
    },
    "resourceId": {
     "videoId": "xRA2M0hcpxY"
    }
   }
  },
  {
   "snippet": {
    "title": "OMS: O que é o coronavírus?",
    "thumbnails": {
     "high": {
      "url": "https://i.ytimg.com/vi/CSaRwi0DdGQ/hqdefault.jpg"
     }
    },
    "resourceId": {
     "videoId": "CSaRwi0DdGQ"
    }
   }
  },
  {
   "snippet": {
    "title": "Destaque ONU News Especial: Santos Cruz fala sobre missão à República Democrática do Congo",
    "thumbnails": {
     "high": {
      "url": "https://i.ytimg.com/vi/2a69nH1KUwk/hqdefault.jpg"
     }
    },
    "resourceId": {
     "videoId": "2a69nH1KUwk"
    }
   }
  },
  {
   "snippet": {
    "title": "ONU News no Globo Notícia Américas - assassinato de ativistas na Colômbia",
    "thumbnails": {
     "high": {
      "url": "https://i.ytimg.com/vi/rYUJCLLQAd8/hqdefault.jpg"
     }
    },
    "resourceId": {
     "videoId": "rYUJCLLQAd8"
    }
   }
  },
  {
   "snippet": {
    "title": "Esperança para a Líbia após Conferência em Berlim",
    "thumbnails": {
     "high": {
      "url": "https://i.ytimg.com/vi/IBSA0eIXXmg/hqdefault.jpg"
     }
    },
    "resourceId": {
     "videoId": "IBSA0eIXXmg"
    }
   }
  },
  {
   "snippet": {
    "title": "Impunidade em assassinatos de jornalistas preocupa Unesco",
    "thumbnails": {
     "high": {
      "url": "https://i.ytimg.com/vi/0F7i_m1nMX4/hqdefault.jpg"
     }
    },
    "resourceId": {
     "videoId": "0F7i_m1nMX4"
    }
   }
  },
  {
   "snippet": {
    "title": "Conferência sobre a Líbia, assassinatos de jornalistas em 2019 e tropas femininas em missão de paz",
    "thumbnails": {
     "high": {
      "url": "https://i.ytimg.com/vi/giY3XKBlzN8/hqdefault.jpg"
     }
    },
    "resourceId": {
     "videoId": "giY3XKBlzN8"
    }
   }
  }
 ]
}
