{
  "items": [
    {
      "snippet": {
        "title": "Vice-presidente do Brasil analisa Conselho de Segurança #shorts",
        "thumbnails": {
          "high": {
            "url": "https://i.ytimg.com/vi/mx2xuMvBnXM/hqdefault.jpg"
          }
        },
        "resourceId": {
          "videoId": "mx2xuMvBnXM"
        }
      }
    },
    {
      "snippet": {
        "title": "\"Aquele que população brasileira eleger irá tomar posse\" #shorts",
        "thumbnails": {
          "high": {
            "url": "https://i.ytimg.com/vi/sabZigoMzFE/hqdefault.jpg"
          }
        },
        "resourceId": {
          "videoId": "sabZigoMzFE"
        }
      }
    },
    {
      "snippet": {
        "title": "Vice-presidente do Brasil, Hamilton Mourão, fala à ONU News sobre Haiti, Ucrânia e eleições",
        "thumbnails": {
          "high": {
            "url": "https://i.ytimg.com/vi/FVwTGI4buVo/hqdefault.jpg"
          }
        },
        "resourceId": {
          "videoId": "FVwTGI4buVo"
        }
      }
    },
    {
      "snippet": {
        "title": "OMS saúda recorde de 99,2% de imunização contra pólio na Guiné-Bissau",
        "thumbnails": {
          "high": {
            "url": "https://i.ytimg.com/vi/C4uaC1vRUlY/hqdefault.jpg"
          }
        },
        "resourceId": {
          "videoId": "C4uaC1vRUlY"
        }
      }
    },
    {
      "snippet": {
        "title": "Mulheres e ações pós-conferência de Lisboa #shorts",
        "thumbnails": {
          "high": {
            "url": "https://i.ytimg.com/vi/UXrcZae7Phk/hqdefault.jpg"
          }
        },
        "resourceId": {
          "videoId": "UXrcZae7Phk"
        }
      }
    },
    {
      "snippet": {
        "title": "Angola e a Declaração de Lisboa sobre oceanos #shorts",
        "thumbnails": {
          "high": {
            "url": "https://i.ytimg.com/vi/BctjjMdd-7k/hqdefault.jpg"
          }
        },
        "resourceId": {
          "videoId": "BctjjMdd-7k"
        }
      }
    },
    {
      "snippet": {
        "title": "Presidente de Portugal diz que “Brasil é grande potência” ao comentar Bicentenário da Independência",
        "thumbnails": {
          "high": {
            "url": "https://i.ytimg.com/vi/TpeN4WItteY/hqdefault.jpg"
          }
        },
        "resourceId": {
          "videoId": "TpeN4WItteY"
        }
      }
    },
    {
      "snippet": {
        "title": "Família Schurmann segue expedição para acelerar fim da poluição plástica nos mares",
        "thumbnails": {
          "high": {
            "url": "https://i.ytimg.com/vi/HMa5cDZUkgY/hqdefault.jpg"
          }
        },
        "resourceId": {
          "videoId": "HMa5cDZUkgY"
        }
      }
    },
    {
      "snippet": {
        "title": "Guiné-Bissau destaca rumo aos ODS",
        "thumbnails": {
          "high": {
            "url": "https://i.ytimg.com/vi/hdq7rmpNfqM/hqdefault.jpg"
          }
        },
        "resourceId": {
          "videoId": "hdq7rmpNfqM"
        }
      }
    },
    {
      "snippet": {
        "title": "Destaque ONU News: Presidência brasileira no Conselho de Segurança e mostra sobre Rui Barbosa",
        "thumbnails": {
          "high": {
            "url": "https://i.ytimg.com/vi/bnY8_zkiglo/hqdefault.jpg"
          }
        },
        "resourceId": {
          "videoId": "bnY8_zkiglo"
        }
      }
    }
  ]
}
