{
  "items": [
    {
      "snippet": {
        "title": "“A política é arte do encontro”, afirma ex-ministra do Mar de Portugal",
        "thumbnails": {
          "high": {
            "url": "https://i.ytimg.com/vi/qiNN_0jdKRo/hqdefault.jpg"
          }
        },
        "resourceId": {
          "videoId": "qiNN_0jdKRo"
        }
      }
    },
    {
      "snippet": {
        "title": "Virando as Marés para o Oceano: Cinco Principais Resultados da Conferência do Oceano",
        "thumbnails": {
          "high": {
            "url": "https://i.ytimg.com/vi/Jbw6RP9qzcY/hqdefault.jpg"
          }
        },
        "resourceId": {
          "videoId": "Jbw6RP9qzcY"
        }
      }
    },
    {
      "snippet": {
        "title": "ONU News traz bastidores da Conferência dos Oceanos em Portugal",
        "thumbnails": {
          "high": {
            "url": "https://i.ytimg.com/vi/G7BltB2Khwc/hqdefault.jpg"
          }
        },
        "resourceId": {
          "videoId": "G7BltB2Khwc"
        }
      }
    },
    {
      "snippet": {
        "title": "Primeiro-ministro de Portugal, António Costa, fala à ONU News sobre Conferência dos Oceanos #Shorts",
        "thumbnails": {
          "high": {
            "url": "https://i.ytimg.com/vi/9bO-8OdFR-Y/hqdefault.jpg"
          }
        },
        "resourceId": {
          "videoId": "9bO-8OdFR-Y"
        }
      }
    },
    {
      "snippet": {
        "title": "Declaração de Lisboa marca encerramento da Conferência dos Oceanos da ONU",
        "thumbnails": {
          "high": {
            "url": "https://i.ytimg.com/vi/lsIrmFVYn30/hqdefault.jpg"
          }
        },
        "resourceId": {
          "videoId": "lsIrmFVYn30"
        }
      }
    },
    {
      "snippet": {
        "title": "Brasil assume presidência do Conselho de Segurança da ONU em julho",
        "thumbnails": {
          "high": {
            "url": "https://i.ytimg.com/vi/Cz00uMcE3aU/hqdefault.jpg"
          }
        },
        "resourceId": {
          "videoId": "Cz00uMcE3aU"
        }
      }
    },
    {
      "snippet": {
        "title": "ACP diz que questão dos mares é existencial",
        "thumbnails": {
          "high": {
            "url": "https://i.ytimg.com/vi/9C5x-GUdcv8/hqdefault.jpg"
          }
        },
        "resourceId": {
          "videoId": "9C5x-GUdcv8"
        }
      }
    },
    {
      "snippet": {
        "title": "Sylvia Earle na Conferência dos Oceanos da ONU",
        "thumbnails": {
          "high": {
            "url": "https://i.ytimg.com/vi/Wy3O6KThmuI/hqdefault.jpg"
          }
        },
        "resourceId": {
          "videoId": "Wy3O6KThmuI"
        }
      }
    },
    {
      "snippet": {
        "title": "Entrevista: Emanuel Gonçalves, cientista-chefe da Fundação Oceano Azul",
        "thumbnails": {
          "high": {
            "url": "https://i.ytimg.com/vi/DgdqvGPSmVY/hqdefault.jpg"
          }
        },
        "resourceId": {
          "videoId": "DgdqvGPSmVY"
        }
      }
    },
    {
      "snippet": {
        "title": "Discurso do primeiro-ministro de São Tomé e Príncipe",
        "thumbnails": {
          "high": {
            "url": "https://i.ytimg.com/vi/AUFVcmILVT4/hqdefault.jpg"
          }
        },
        "resourceId": {
          "videoId": "AUFVcmILVT4"
        }
      }
    }
  ]
}
