{
  "items": [
    {
      "snippet": {
        "title": "O que faz o Banco Mundial?",
        "thumbnails": {
          "high": {
            "url": "https://i.ytimg.com/vi/ZV6mvSJECDE/hqdefault.jpg"
          }
        },
        "resourceId": {
          "videoId": "ZV6mvSJECDE"
        }
      }
    },
    {
      "snippet": {
        "title": "Desafios da pandemia inspiram música no Brasil",
        "thumbnails": {
          "high": {
            "url": "https://i.ytimg.com/vi/bgwfbWGPEHM/hqdefault.jpg"
          }
        },
        "resourceId": {
          "videoId": "bgwfbWGPEHM"
        }
      }
    },
    {
      "snippet": {
        "title": "Brasil recebe 3,9 milhões de vacinas contra Covid-19 via Covax",
        "thumbnails": {
          "high": {
            "url": "https://i.ytimg.com/vi/I1g4BqxXFoM/hqdefault.jpg"
          }
        },
        "resourceId": {
          "videoId": "I1g4BqxXFoM"
        }
      }
    },
    {
      "snippet": {
        "title": "Escritório de Direitos Humanos da ONU pede investigação de operação policial no Rio de Janeiro",
        "thumbnails": {
          "high": {
            "url": "https://i.ytimg.com/vi/lvHFBxkzoZA/hqdefault.jpg"
          }
        },
        "resourceId": {
          "videoId": "lvHFBxkzoZA"
        }
      }
    },
    {
      "snippet": {
        "title": "Cabo Verde ressalta inovação e modernidade no Dia Mundial da Língua Portuguesa",
        "thumbnails": {
          "high": {
            "url": "https://i.ytimg.com/vi/y2o_lmcYexQ/hqdefault.jpg"
          }
        },
        "resourceId": {
          "videoId": "y2o_lmcYexQ"
        }
      }
    },
    {
      "snippet": {
        "title": "Mensagem do secretário-geral da ONU para o Dia Mundial da Língua Portuguesa",
        "thumbnails": {
          "high": {
            "url": "https://i.ytimg.com/vi/lLYGtybbqck/hqdefault.jpg"
          }
        },
        "resourceId": {
          "videoId": "lLYGtybbqck"
        }
      }
    },
    {
      "snippet": {
        "title": "Ivan Lins fala do diferencial da língua portuguesa",
        "thumbnails": {
          "high": {
            "url": "https://i.ytimg.com/vi/_dkkujif4B8/hqdefault.jpg"
          }
        },
        "resourceId": {
          "videoId": "_dkkujif4B8"
        }
      }
    },
    {
      "snippet": {
        "title": "Fernando Henrique Cardoso expressa sua relação com a língua portuguesa",
        "thumbnails": {
          "high": {
            "url": "https://i.ytimg.com/vi/pAi5hVARi2M/hqdefault.jpg"
          }
        },
        "resourceId": {
          "videoId": "pAi5hVARi2M"
        }
      }
    },
    {
      "snippet": {
        "title": "Presidente do Camões destaca importância de promover língua portuguesa",
        "thumbnails": {
          "high": {
            "url": "https://i.ytimg.com/vi/i5g-3l9pR9c/hqdefault.jpg"
          }
        },
        "resourceId": {
          "videoId": "i5g-3l9pR9c"
        }
      }
    },
    {
      "snippet": {
        "title": "Mensagem da Cplp sobre o Dia Mundial da Língua Portuguesa",
        "thumbnails": {
          "high": {
            "url": "https://i.ytimg.com/vi/8xdmrPxc4kY/hqdefault.jpg"
          }
        },
        "resourceId": {
          "videoId": "8xdmrPxc4kY"
        }
      }
    }
  ]
}
