{
 "items": [
  {
   "snippet": {
    "title": "Опасность бедствий",
    "thumbnails": {
     "high": {
      "url": "https://i.ytimg.com/vi/-IkxHv3vTNM/hqdefault.jpg"
     }
    },
    "resourceId": {
     "videoId": "-IkxHv3vTNM"
    }
   }
  },
  {
   "snippet": {
    "title": "Алексей Леонов: «А Земля-то ведь круглая!»",
    "thumbnails": {
     "high": {
      "url": "https://i.ytimg.com/vi/teiM6WNQW-E/hqdefault.jpg"
     }
    },
    "resourceId": {
     "videoId": "teiM6WNQW-E"
    }
   }
  },
  {
   "snippet": {
    "title": "Туфли для школьниц в Бенине",
    "thumbnails": {
     "high": {
      "url": "https://i.ytimg.com/vi/sNBuFhuU90Y/hqdefault.jpg"
     }
    },
    "resourceId": {
     "videoId": "sNBuFhuU90Y"
    }
   }
  },
  {
   "snippet": {
    "title": "Всемирный день зрения",
    "thumbnails": {
     "high": {
      "url": "https://i.ytimg.com/vi/yVFxeHJXyrg/hqdefault.jpg"
     }
    },
    "resourceId": {
     "videoId": "yVFxeHJXyrg"
    }
   }
  },
  {
   "snippet": {
    "title": "«Война и мир» в Женеве",
    "thumbnails": {
     "high": {
      "url": "https://i.ytimg.com/vi/fF2bd4Opm1c/hqdefault.jpg"
     }
    },
    "resourceId": {
     "videoId": "fF2bd4Opm1c"
    }
   }
  },
  {
   "snippet": {
    "title": "Азизбек Ашуров",
    "thumbnails": {
     "high": {
      "url": "https://i.ytimg.com/vi/ah5d9JCN3mM/hqdefault.jpg"
     }
    },
    "resourceId": {
     "videoId": "ah5d9JCN3mM"
    }
   }
  },
  {
   "snippet": {
    "title": "Дневник 74-ой сессии Генассамблеи ООН. Заключительный выпуск",
    "thumbnails": {
     "high": {
      "url": "https://i.ytimg.com/vi/qWKer3RoAoQ/hqdefault.jpg"
     }
    },
    "resourceId": {
     "videoId": "qWKer3RoAoQ"
    }
   }
  },
  {
   "snippet": {
    "title": "Джейсон Момоа",
    "thumbnails": {
     "high": {
      "url": "https://i.ytimg.com/vi/u2IvHMmbhnU/hqdefault.jpg"
     }
    },
    "resourceId": {
     "videoId": "u2IvHMmbhnU"
    }
   }
  },
  {
   "snippet": {
    "title": "Дневник Генассамблеи ООН 27 сентября",
    "thumbnails": {
     "high": {
      "url": "https://i.ytimg.com/vi/aeqelIaVrNg/hqdefault.jpg"
     }
    },
    "resourceId": {
     "videoId": "aeqelIaVrNg"
    }
   }
  },
  {
   "snippet": {
    "title": "Лучше 10 лет переговоров, чем 1 день войны -  С.Лавров открыл в ООН выставку о А.Громыко",
    "thumbnails": {
     "high": {
      "url": "https://i.ytimg.com/vi/KCs5v2CHQKk/hqdefault.jpg"
     }
    },
    "resourceId": {
     "videoId": "KCs5v2CHQKk"
    }
   }
  }
 ]
}
